fabricatio_capabilities/__init__.py
fabricatio_capabilities/config.py
fabricatio_capabilities/py.typed
fabricatio_capabilities/actions/__init__.py
fabricatio_capabilities/capabilities/__init__.py
fabricatio_capabilities/capabilities/extract.py
fabricatio_capabilities/capabilities/order.py
fabricatio_capabilities/capabilities/rating.py
fabricatio_capabilities/capabilities/task.py
fabricatio_capabilities/models/__init__.py
fabricatio_capabilities/models/generic.py
fabricatio_capabilities/models/kwargs_types.py
fabricatio_capabilities/workflows/__init__.py
tests/test_order.py
fabricatio_capabilities-0.3.8.dist-info/METADATA
fabricatio_capabilities-0.3.8.dist-info/WHEEL
fabricatio_capabilities-0.3.8.dist-info/licenses/LICENSE
fabricatio_capabilities-0.3.8.dist-info/RECORD
