Metadata-Version: 2.4
Name: fabricatio-capabilities
Version: 0.3.8
Summary: A foundational Python library providing core capabilities for building LLM-driven applications using an event-based agent structure.
Project-URL: Homepage, https://github.com/Whth/fabricatio
Project-URL: Repository, https://github.com/Whth/fabricatio
Project-URL: Issues, https://github.com/Whth/fabricatio/issues
Author-email: Whth <zettainspector@foxmail.com>
License: MIT License
License-File: LICENSE
Classifier: Framework :: AsyncIO
Classifier: Framework :: Pydantic :: 2
Classifier: License :: OSI Approved :: MIT License
Classifier: Programming Language :: Python :: 3.12
Classifier: Programming Language :: Python :: 3.13
Classifier: Programming Language :: Python :: 3.14
Classifier: Programming Language :: Python :: Implementation :: CPython
Classifier: Typing :: Typed
Requires-Python: <3.15,>=3.12
Requires-Dist: fabricatio-core
Requires-Dist: orjson>=3.10.18
